plawt
