Metadata-Version: 1.1
Name: plawt
Version: 1.1.10
Summary: JSON-like sugar for plotting with matplotlib
Home-page: https://github.com/mef51/plawt
Author: Mohammed Chamma
Author-email: hms.mohammed@gmail.com
License: MIT
Keywords: plotting matplotlib science sugar wrapper
Platform: UNKNOWN
Classifier: Programming Language :: Python :: 2
Classifier: Programming Language :: Python :: 3
